{"$schema":"https://schema.tauri.app/config/2","productName":"Pulse","version":"1.0.8","identifier":"app.pulse.launcher","build":{"beforeDevCommand":"npm run dev","devUrl":"http://localhost:1420","beforeBuildCommand":"npm run build","frontendDist":"../dist"},"app":{"windows":[{"title":"Pulse","width":1280,"height":720,"shadow":true,"resizable":false,"maximizable":false,"label":"main","visible":true,"decorations":false}],"security":{"csp":null}},"bundle":{"active":true,"targets":"all","createUpdaterArtifacts":true,"icon":["icons/32x32.png","icons/128x128.png","icons/128x128@2x.png","icons/icon.icns","icons/icon.ico"]},"plugins":{"deep-link":{"desktop":{"schemes":["pulse","vortyx","crystal"]}},"updater":{"windows":{"installMode":"passive"},"enabled":true,"pubkey":"dW50cnVzdGVkIGNvbW1lbnQ6IG1pbmlzaWduIHB1YmxpYyBrZXk6IEZCMEVDM0M1QTU5RDE3RkIKUldUN0Y1Mmx4Y01PKzhvMWpLaXFIREpVOE5YeWN0bFJUbzVwd0Z3NWJyMUM2aXVuYzI4eXZvcjEK","endpoints":["https://dl.netcable.dev/pulse/launcher/tauri.json"]}}}
